simpledft/__init__.py
simpledft/atoms.py
simpledft/dft.py
simpledft/energies.py
simpledft/minimizer.py
simpledft/operators.py
simpledft/potentials.py
simpledft/scf.py
simpledft/utils.py
simpledft/xc.py
simpledft-3.0.dist-info/LICENSE
simpledft-3.0.dist-info/METADATA
simpledft-3.0.dist-info/WHEEL
simpledft-3.0.dist-info/top_level.txt
simpledft-3.0.dist-info/RECORD
