Metadata-Version: 2.1
Name: simpledft
Version: 3.0
Summary: A simple density functional theory code.
Author-email: Wanja Timm Schulze <wangenau@protonmail.com>
Project-URL: Documentation, https://wangenau.gitlab.io/simpledft_pages
Project-URL: Issues, https://gitlab.com/wangenau/simpledft/-/issues
Classifier: Development Status :: 5 - Production/Stable
Classifier: Intended Audience :: Developers
Classifier: Intended Audience :: Education
Classifier: Intended Audience :: Science/Research
Classifier: License :: OSI Approved
Classifier: License :: OSI Approved :: Apache Software License
Classifier: Programming Language :: Python
Classifier: Programming Language :: Python :: 3
Classifier: Programming Language :: Python :: 3 :: Only
Classifier: Topic :: Education
Classifier: Topic :: Scientific/Engineering
Classifier: Topic :: Scientific/Engineering :: Chemistry
Classifier: Topic :: Scientific/Engineering :: Physics
Classifier: Topic :: Software Development
Requires-Python: >=3.5
License-File: LICENSE
Requires-Dist: numpy >=1.10
